seguin_loom_server/__init__.py
seguin_loom_server/favicon-32x32.png
seguin_loom_server/loom_server.py
seguin_loom_server/main.py
seguin_loom_server/mock_loom.py
seguin_loom_server/py.typed
seguin_loom_server/version.py
seguin_loom_server-0.12.dist-info/licenses/LICENSE.txt
seguin_loom_server-0.12.dist-info/METADATA
seguin_loom_server-0.12.dist-info/WHEEL
seguin_loom_server-0.12.dist-info/entry_points.txt
seguin_loom_server-0.12.dist-info/top_level.txt
seguin_loom_server-0.12.dist-info/RECORD
