Metadata-Version: 2.4
Name: seguin_loom_server
Version: 0.12
Summary: Web server that drives a Séguin dobby loom
Author-email: Russell Owen <r3owen@gmail.com>
Project-URL: Homepage, https://pypi.org/project/seguin-loom-server/
Project-URL: Documentation, https://r-owen.github.io/base_loom_server/
Project-URL: Source, https://github.com/r-owen/seguin_loom_server
Project-URL: Issues, https://github.com/r-owen/seguin_loom_server/issues
Classifier: Programming Language :: Python :: 3
Classifier: License :: OSI Approved :: MIT License
Classifier: Operating System :: OS Independent
Requires-Python: >=3.11
License-File: LICENSE.txt
Requires-Dist: base_loom_server>=1.0
Provides-Extra: dev
Requires-Dist: base_loom_server[dev]>=1.0; extra == "dev"
Dynamic: license-file
